<?xml version='1.0' encoding='utf-8'?>
<list maintainEnchantment="true">
  <item id="2">
    <ingredient id="57" count="10"/>
    <production id="9546" count="1"/>
  </item>
  <item id="2">
    <ingredient id="57" count="10"/>
    <production id="9547" count="1"/>
  </item>
  <item id="2">
    <ingredient id="57" count="10"/>
    <production id="9548" count="1"/>
  </item>
  <item id="2">
    <ingredient id="57" count="10"/>
    <production id="9549" count="1"/>
  </item>
  <item id="2">
    <ingredient id="57" count="10"/>
    <production id="9550" count="1"/>
  </item>
  <item id="2">
    <ingredient id="57" count="10"/>
    <production id="9551" count="1"/>
  </item>
  <item id="2">
    <ingredient id="9546" count="5"/>
    <production id="9552" count="1"/>
  </item>
  <item id="2">
    <ingredient id="9547" count="5"/>
    <production id="9553" count="1"/>
  </item>
  <item id="2">
    <ingredient id="9548" count="5"/>
    <production id="9554" count="1"/>
  </item>
  <item id="2">
    <ingredient id="9549" count="5"/>
    <production id="9555" count="1"/>
  </item>
  <item id="2">
    <ingredient id="9550" count="5"/>
    <production id="9556" count="1"/>
  </item>
  <item id="2">
    <ingredient id="9551" count="5"/>
    <production id="9557" count="1"/>
  </item>
  <item id="2">
    <ingredient id="57" count="5"/>
    <production id="8762" count="1"/>
  </item>
  <item id="2">
    <ingredient id="57" count="5"/>
    <production id="9576" count="1"/>
  </item>
  <item id="2">
    <ingredient id="57" count="5"/>
    <production id="16167" count="1"/>
  </item>
  <item id="2">
    <ingredient id="57" count="5"/>
    <production id="12849" count="1"/>
  </item>
  <item id="2">
    <ingredient id="57" count="5"/>
    <production id="12850" count="1"/>
  </item>
  <item id="2">
    <ingredient id="57" count="5"/>
    <production id="16178" count="1"/>
  </item>
  <item id="2">
    <ingredient id="57" count="5"/>
    <production id="955" count="1"/>
  </item>
  <item id="2">
    <ingredient id="57" count="5"/>
    <production id="22006" count="1"/>
  </item>
  <item id="2">
    <ingredient id="57" count="5"/>
    <production id="22008" count="1"/>
  </item>
  <item id="2">
    <ingredient id="57" count="5"/>
    <production id="22009" count="1"/>
  </item>
  <item id="2">
    <ingredient id="57" count="5"/>
    <production id="959" count="1"/>
  </item>
  <item id="2">
    <ingredient id="57" count="5"/>
    <production id="6575" count="1"/>
  </item>
  <item id="2">
    <ingredient id="57" count="5"/>
    <production id="6573" count="1"/>
  </item>
  <item id="2">
    <ingredient id="57" count="5"/>
    <production id="6571" count="1"/>
  </item>
  <item id="2">
    <ingredient id="57" count="5"/>
    <production id="6569" count="1"/>
  </item>
  <item id="2">
    <ingredient id="57" count="5"/>
    <production id="6577" count="1"/>
  </item>
  <item id="2">
    <ingredient id="57" count="5"/>
    <production id="4635" count="1"/>
  </item>
  <item id="2">
    <ingredient id="57" count="5"/>
    <production id="4636" count="1"/>
  </item>
  <item id="2">
    <ingredient id="57" count="5"/>
    <production id="4637" count="1"/>
  </item>
  <item id="2">
    <ingredient id="57" count="5"/>
    <production id="4638" count="1"/>
  </item>
  <item id="2">
    <ingredient id="57" count="5"/>
    <production id="4639" count="1"/>
  </item>
  <item id="2">
    <ingredient id="57" count="5"/>
    <production id="5577" count="1"/>
  </item>
  <item id="2">
    <ingredient id="57" count="5"/>
    <production id="5580" count="1"/>
  </item>
  <item id="2">
    <ingredient id="57" count="5"/>
    <production id="5908" count="1"/>
  </item>
  <item id="2">
    <ingredient id="57" count="5"/>
    <production id="9570" count="1"/>
  </item>
  <item id="2">
    <ingredient id="57" count="5"/>
    <production id="10480" count="1"/>
  </item>
  <item id="2">
    <ingredient id="57" count="5"/>
    <production id="13071" count="1"/>
  </item>
  <item id="2">
    <ingredient id="57" count="5"/>
    <production id="15541" count="1"/>
  </item>
  <item id="2">
    <ingredient id="57" count="5"/>
    <production id="15826" count="1"/>
  </item>
  <item id="2">
    <ingredient id="57" count="5"/>
    <production id="4646" count="1"/>
  </item>
  <item id="2">
    <ingredient id="57" count="5"/>
    <production id="4647" count="1"/>
  </item>
  <item id="2">
    <ingredient id="57" count="5"/>
    <production id="4648" count="1"/>
  </item>
  <item id="2">
    <ingredient id="57" count="5"/>
    <production id="4649" count="1"/>
  </item>
  <item id="2">
    <ingredient id="57" count="5"/>
    <production id="4650" count="1"/>
  </item>
  <item id="2">
    <ingredient id="57" count="5"/>
    <production id="5578" count="1"/>
  </item>
  <item id="2">
    <ingredient id="57" count="5"/>
    <production id="5581" count="1"/>
  </item>
  <item id="2">
    <ingredient id="57" count="5"/>
    <production id="5911" count="1"/>
  </item>
  <item id="2">
    <ingredient id="57" count="5"/>
    <production id="9572" count="1"/>
  </item>
  <item id="2">
    <ingredient id="57" count="5"/>
    <production id="10482" count="1"/>
  </item>
  <item id="2">
    <ingredient id="57" count="5"/>
    <production id="13073" count="1"/>
  </item>
  <item id="2">
    <ingredient id="57" count="5"/>
    <production id="15543" count="1"/>
  </item>
  <item id="2">
    <ingredient id="57" count="5"/>
    <production id="15828" count="1"/>
  </item>
  <item id="2">
    <ingredient id="57" count="5"/>
    <production id="4657" count="1"/>
  </item>
  <item id="2">
    <ingredient id="57" count="5"/>
    <production id="4658" count="1"/>
  </item>
  <item id="2">
    <ingredient id="57" count="5"/>
    <production id="4659" count="1"/>
  </item>
  <item id="2">
    <ingredient id="57" count="5"/>
    <production id="4660" count="1"/>
  </item>
  <item id="2">
    <ingredient id="57" count="5"/>
    <production id="4661" count="1"/>
  </item>
  <item id="2">
    <ingredient id="57" count="5"/>
    <production id="5579" count="1"/>
  </item>
  <item id="2">
    <ingredient id="57" count="5"/>
    <production id="5582" count="1"/>
  </item>
  <item id="2">
    <ingredient id="57" count="5"/>
    <production id="5914" count="1"/>
  </item>
  <item id="2">
    <ingredient id="57" count="5"/>
    <production id="9571" count="1"/>
  </item>
  <item id="2">
    <ingredient id="57" count="5"/>
    <production id="10481" count="1"/>
  </item>
  <item id="2">
    <ingredient id="57" count="5"/>
    <production id="13072" count="1"/>
  </item>
  <item id="2">
    <ingredient id="57" count="5"/>
    <production id="15542" count="1"/>
  </item>
  <item id="2">
    <ingredient id="57" count="5"/>
    <production id="15827" count="1"/>
  </item>
</list>