<?xml version="1.0" encoding="UTF-8"?>

<list>
	<armor id="18100" name="Благословенное Ожерелье Айдиоса" type="NONE">
		<!--Done By ALF (c)L2-WT-->
		<set name="bodypart" val="NECK"/>
		<set name="icon" val="icon.r991_necklace_i00"/>
		<set name="weight" val="150"/>
		<set name="crystal_type" val="R99"/>
		<set name="crystal_count" val="1106"/>
		<set name="m_def" val="166"/>
		<set name="mp_bonus" val="65"/>
	</armor>
	<armor id="18101" name="Благословенная Серьга Айдиоса" type="NONE">
		<!--Done By ALF (c)L2-WT-->
		<set name="bodypart" val="LREAR"/>
		<set name="icon" val="icon.r991_earring_i00"/>
		<set name="weight" val="150"/>
		<set name="crystal_type" val="R99"/>
		<set name="crystal_count" val="826"/>
		<set name="m_def" val="124"/>
		<set name="mp_bonus" val="49"/>
	</armor>
	<armor id="18102" name="Благословенное Кольцо Айдиоса" type="NONE">
		<!--Done By ALF (c)L2-WT-->
		<set name="bodypart" val="LRFINGER"/>
		<set name="icon" val="icon.r991_ring_i00"/>
		<set name="weight" val="150"/>
		<set name="crystal_type" val="R99"/>
		<set name="crystal_count" val="553"/>
		<set name="m_def" val="83"/>
		<set name="mp_bonus" val="33"/>
	</armor>
</list>
